NJU/P6/T3/top.v
module top(
	input [63:0] in,
	input clk,
	input load,
	output reg [63:0] out
);
	reg [63:0] state;
	always@(posedge clk)begin
		if(load)begin
			state <= in;
		end else begin
			state <= {state[62:0], state[4]^state[3]^state[2]^state[0]};
		end
		out <= state;
	end
	endmodule

NJU/P6/T3/dump.vcd
$version Generated by VerilatedVcd $end
$timescale 1s $end

 $scope module TOP $end
  $var wire  1 % clk $end
  $var wire 64 # in [63:0] $end
  $var wire  1 & load $end
  $var wire 64 ' out [63:0] $end
  $scope module top $end
   $var wire  1 % clk $end
   $var wire 64 # in [63:0] $end
   $var wire  1 & load $end
   $var wire 64 ' out [63:0] $end
   $var wire 64 ) state [63:0] $end
  $upscope $end
 $upscope $end
$enddefinitions $end


#1
b0000000000000000000000000000000000000000000000000000000000000000 #
0%
0&
b0000000000000000000000000000000000000000000000000000000000000000 '
b0000000000000000000000000000000000000000000000000000000000000000 )
#2
b0001001000110100010101100111100010011010101111001101111011110000 #
1&
#3
1%
b0001001000110100010101100111100010011010101111001101111011110000 )
#4
0%
0&
#5
1%
b0001001000110100010101100111100010011010101111001101111011110000 '
b0010010001101000101011001111000100110101011110011011110111100001 )
#6
0%
#7
1%
b0010010001101000101011001111000100110101011110011011110111100001 '
b0100100011010001010110011110001001101010111100110111101111000011 )
#8
0%
#9
1%
b0100100011010001010110011110001001101010111100110111101111000011 '
b1001000110100010101100111100010011010101111001101111011110000111 )
#10
0%
#11
1%
b1001000110100010101100111100010011010101111001101111011110000111 '
b0010001101000101011001111000100110101011110011011110111100001110 )
#12
0%
#13
1%
b0010001101000101011001111000100110101011110011011110111100001110 '
b0100011010001010110011110001001101010111100110111101111000011100 )
#14
0%
#15
1%
b0100011010001010110011110001001101010111100110111101111000011100 '
b1000110100010101100111100010011010101111001101111011110000111001 )
#16
0%
#17
1%
b1000110100010101100111100010011010101111001101111011110000111001 '
b0001101000101011001111000100110101011110011011110111100001110011 )
#18
0%
#19
1%
b0001101000101011001111000100110101011110011011110111100001110011 '
b0011010001010110011110001001101010111100110111101111000011100110 )
#20
0%
#21
1%
b0011010001010110011110001001101010111100110111101111000011100110 '
b0110100010101100111100010011010101111001101111011110000111001101 )
#22
0%
#23
1%
b0110100010101100111100010011010101111001101111011110000111001101 '
b1101000101011001111000100110101011110011011110111100001110011011 )
