NJU/P1/T2/mux41.v
module mux41(a,s,y);
  input  [3:0] a;
  input  [1:0] s;
  output y;
  MuxKeyWithDefault #(4, 2, 1) i0 (y, s, 1'b0, {
    2'b00, a[0],
    2'b01, a[1],
    2'b10, a[2],
    2'b11, a[3]
  });
endmodule
/* verilator lint_off DECLFILENAME */
module MuxKeyWithDefault #(NR_KEY = 2, KEY_LEN = 1, DATA_LEN = 1) (
  output [DATA_LEN-1:0] out,
  input [KEY_LEN-1:0] key,
  input [DATA_LEN-1:0] default_out,
  input [NR_KEY*(KEY_LEN + DATA_LEN)-1:0] lut
);
  MuxKeyInternal #(NR_KEY, KEY_LEN, DATA_LEN, 1) i0 (out, key, default_out, lut);
endmodule

module MuxKeyInternal #(NR_KEY = 2, KEY_LEN = 1, DATA_LEN = 1, HAS_DEFAULT = 0) (
  output reg [DATA_LEN-1:0] out,
  input [KEY_LEN-1:0] key,
  input [DATA_LEN-1:0] default_out,
  input [NR_KEY*(KEY_LEN + DATA_LEN)-1:0] lut
);

  localparam PAIR_LEN = KEY_LEN + DATA_LEN;
  wire [PAIR_LEN-1:0] pair_list [NR_KEY-1:0];
  wire [KEY_LEN-1:0] key_list [NR_KEY-1:0];
  wire [DATA_LEN-1:0] data_list [NR_KEY-1:0];

  generate
    for (genvar n = 0; n < NR_KEY; n = n + 1) begin
      assign pair_list[n] = lut[PAIR_LEN*(n+1)-1 : PAIR_LEN*n];
      assign data_list[n] = pair_list[n][DATA_LEN-1:0];
      assign key_list[n]  = pair_list[n][PAIR_LEN-1:DATA_LEN];
    end
  endgenerate

  reg [DATA_LEN-1 : 0] lut_out;
  reg hit;
  integer i;
  always @(*) begin
    lut_out = 0;
    hit = 0;
    for (i = 0; i < NR_KEY; i = i + 1) begin
      lut_out = lut_out | ({DATA_LEN{key == key_list[i]}} & data_list[i]);
      hit = hit | (key == key_list[i]);
    end
    if (!HAS_DEFAULT) out = lut_out;
    else out = (hit ? lut_out : default_out);
  end

endmodule
/* verilator lint_on DECLFILENAME */

NJU/P1/T2/dump.vcd
$version Generated by VerilatedVcd $end
$timescale 1s $end

 $scope module TOP $end
  $var wire  4 1 a [3:0] $end
  $var wire  2 2 s [1:0] $end
  $var wire  1 3 y $end
  $scope module mux41 $end
   $var wire  4 1 a [3:0] $end
   $var wire  2 2 s [1:0] $end
   $var wire  1 3 y $end
   $scope module i0 $end
    $var wire 32 7 DATA_LEN [31:0] $end
    $var wire 32 6 KEY_LEN [31:0] $end
    $var wire 32 5 NR_KEY [31:0] $end
    $var wire  1 8 default_out [0:0] $end
    $var wire  2 2 key [1:0] $end
    $var wire 12 4 lut [11:0] $end
    $var wire  1 3 out [0:0] $end
    $scope module i0 $end
     $var wire 32 7 DATA_LEN [31:0] $end
     $var wire 32 7 HAS_DEFAULT [31:0] $end
     $var wire 32 6 KEY_LEN [31:0] $end
     $var wire 32 5 NR_KEY [31:0] $end
     $var wire 32 9 PAIR_LEN [31:0] $end
     $var wire  1 + data_list[0] [0:0] $end
     $var wire  1 , data_list[1] [0:0] $end
     $var wire  1 - data_list[2] [0:0] $end
     $var wire  1 . data_list[3] [0:0] $end
     $var wire  1 8 default_out [0:0] $end
     $var wire  1 0 hit $end
     $var wire 32 : i [31:0] $end
     $var wire  2 2 key [1:0] $end
     $var wire  2 # key_list[0] [1:0] $end
     $var wire  2 $ key_list[1] [1:0] $end
     $var wire  2 % key_list[2] [1:0] $end
     $var wire  2 & key_list[3] [1:0] $end
     $var wire 12 4 lut [11:0] $end
     $var wire  1 / lut_out [0:0] $end
     $var wire  1 3 out [0:0] $end
     $var wire  3 ' pair_list[0] [2:0] $end
     $var wire  3 ( pair_list[1] [2:0] $end
     $var wire  3 ) pair_list[2] [2:0] $end
     $var wire  3 * pair_list[3] [2:0] $end
    $upscope $end
   $upscope $end
  $upscope $end
 $upscope $end
$enddefinitions $end


#1
b11 #
b10 $
b01 %
b00 &
b111 '
b101 (
b011 )
b000 *
1+
1,
1-
0.
0/
10
b1110 1
b00 2
03
b000011101111 4
b00000000000000000000000000000100 5
b00000000000000000000000000000010 6
b00000000000000000000000000000001 7
08
b00000000000000000000000000000011 9
b00000000000000000000000000000100 :
#2
b110 '
b100 (
b010 )
b001 *
0+
0,
0-
1.
1/
b0001 1
13
b001010100110 4
#3
b111 '
b101 (
b011 )
b000 *
1+
1,
1-
0.
b1110 1
b01 2
b000011101111 4
#4
b110 '
b100 (
0+
0,
b0010 1
b000011100110 4
#5
b111 '
1+
0/
b1010 1
b10 2
03
b000011100111 4
#6
b110 '
b101 (
b010 )
0+
1,
0-
1/
b0100 1
13
b000010101110 4
#7
b011 )
b001 *
1-
1.
0/
b0111 1
b11 2
03
b001011101110 4
#8
b111 '
b100 (
b010 )
1+
0,
0-
1/
b1001 1
13
b001010100111 4
