NJUtest/test3_2/top.v
module top(
	input a,
	input b,
	input ci,
	output so,
	output co
);
	assign so = a ^ b ^ ci;
	assign co = (a&b) | (ci & (a ^ b));
endmodule



//1位全加器

NJUtest/test3_2/dump.vcd
$version Generated by VerilatedVcd $end
$timescale 1s $end

 $scope module TOP $end
  $var wire  1 # a $end
  $var wire  1 $ b $end
  $var wire  1 % ci $end
  $var wire  1 ' co $end
  $var wire  1 & so $end
  $scope module top $end
   $var wire  1 # a $end
   $var wire  1 $ b $end
   $var wire  1 % ci $end
   $var wire  1 ' co $end
   $var wire  1 & so $end
  $upscope $end
 $upscope $end
$enddefinitions $end


#1
0#
0$
0%
0&
0'
#2
1%
1&
#3
1$
0%
#4
1%
0&
1'
#5
1#
0$
0%
1&
0'
#6
1%
0&
1'
#7
1$
0%
#8
1%
1&
