NJUtest/test1_3/top.v
module top(F, Y, X0, X1, X2, X3);
	output reg F;
	input [1:0] Y;
	input X0, X1, X2, X3;
	always@(*)
		case(Y)
			2'b00:F = X0;
			2'b01:F = X1;
			2'b10:F = X2;
			2'b11:F = X3;
			default: F = 1'b00;
		endcase
endmodule

NJUtest/test1_3/dump.vcd
$version Generated by VerilatedVcd $end
$timescale 1s $end

 $scope module TOP $end
  $var wire  1 # F $end
  $var wire  1 % X0 $end
  $var wire  1 & X1 $end
  $var wire  1 ' X2 $end
  $var wire  1 ( X3 $end
  $var wire  2 $ Y [1:0] $end
  $scope module top $end
   $var wire  1 # F $end
   $var wire  1 % X0 $end
   $var wire  1 & X1 $end
   $var wire  1 ' X2 $end
   $var wire  1 ( X3 $end
   $var wire  2 $ Y [1:0] $end
  $upscope $end
 $upscope $end
$enddefinitions $end


#1
0#
b00 $
0%
0&
0'
0(
#2
1#
1%
#3
0#
0%
1&
#4
1#
1%
#5
0#
0%
0&
1'
#6
1#
1%
#7
0#
0%
1&
#8
1#
1%
#9
0#
0%
0&
0'
1(
#10
1#
1%
#11
0#
0%
1&
#12
1#
1%
#13
0#
0%
0&
1'
#14
1#
1%
#15
0#
0%
1&
#16
1#
1%
#17
0#
0%
0&
0'
0(
#18
b01 $
1%
#19
0%
#20
1#
1%
1&
#21
0%
#22
0#
1%
0&
1'
#23
0%
#24
1#
1%
1&
#25
0%
#26
0#
1%
0&
0'
1(
#27
0%
#28
1#
1%
1&
#29
0%
#30
0#
1%
0&
1'
#31
0%
#32
1#
1%
1&
#33
0%
#34
0#
1%
0&
0'
0(
#35
b10 $
0%
#36
1%
#37
0%
1&
#38
1%
#39
1#
0%
0&
1'
#40
1%
#41
0%
1&
#42
1%
#43
0#
0%
0&
0'
1(
#44
1%
#45
0%
1&
#46
1%
#47
1#
0%
0&
1'
#48
1%
#49
0%
1&
#50
1%
#51
0#
0%
0&
0'
0(
#52
b11 $
1%
#53
0%
#54
1%
1&
#55
0%
#56
1%
0&
1'
#57
0%
#58
1%
1&
#59
0%
#60
1#
1%
0&
0'
1(
#61
0%
#62
1%
1&
#63
0%
#64
1%
0&
1'
#65
0%
#66
1%
1&
#67
0%
#68
0#
1%
0&
0'
0(
#69
b00 $
0%
#70
1#
1%
#71
0#
0%
1&
#72
1#
1%
#73
0#
0%
0&
1'
#74
1#
1%
#75
0#
0%
1&
#76
1#
1%
#77
0#
0%
0&
0'
1(
#78
1#
1%
#79
0#
0%
1&
#80
1#
1%
#81
0#
0%
0&
1'
#82
1#
1%
#83
0#
0%
1&
#84
1#
1%
#85
0#
0%
0&
0'
0(
#86
b01 $
1%
